xturing/__about__.py
xturing/__init__.py
xturing/registry.py
xturing/cli/__init__.py
xturing/cli/api.py
xturing/cli/chat.py
xturing/cli/ui.py
xturing/config/__init__.py
xturing/config/config_data_classes.py
xturing/config/finetuning_config.yaml
xturing/config/generation_config.yaml
xturing/config/read_config.py
xturing/datasets/__init__.py
xturing/datasets/base.py
xturing/datasets/instruction_dataset.py
xturing/datasets/text2image_dataset.py
xturing/datasets/text_dataset.py
xturing/engines/__init__.py
xturing/engines/base.py
xturing/engines/bloom_engine.py
xturing/engines/causal.py
xturing/engines/cerebras_engine.py
xturing/engines/distilgpt2_engine.py
xturing/engines/falcon_engine.py
xturing/engines/galactica_engine.py
xturing/engines/generic_engine.py
xturing/engines/gpt2_engine.py
xturing/engines/gptj_engine.py
xturing/engines/llama2_engine.py
xturing/engines/llama_engine.py
xturing/engines/opt_engine.py
xturing/engines/gptj_utils/__init__.py
xturing/engines/gptj_utils/gptj.py
xturing/engines/llama_utils/__init__.py
xturing/engines/llama_utils/llama.py
xturing/engines/lora_engine/__init__.py
xturing/engines/lora_engine/lora.py
xturing/engines/lora_engine/save_and_load.py
xturing/engines/lora_engine/test.py
xturing/engines/quant_utils/__init__.py
xturing/engines/quant_utils/cachedistillationoutputs.py
xturing/engines/quant_utils/custom_autotune.py
xturing/engines/quant_utils/lrec.py
xturing/engines/quant_utils/peft_utils.py
xturing/engines/quant_utils/qerdataloading.py
xturing/engines/quant_utils/quant.py
xturing/model_apis/__init__.py
xturing/model_apis/ai21.py
xturing/model_apis/base.py
xturing/model_apis/cohere.py
xturing/model_apis/openai.py
xturing/models/__init__.py
xturing/models/base.py
xturing/models/bloom.py
xturing/models/causal.py
xturing/models/cerebras.py
xturing/models/distilgpt2.py
xturing/models/falcon.py
xturing/models/galactica.py
xturing/models/generic.py
xturing/models/gpt2.py
xturing/models/gptj.py
xturing/models/llama.py
xturing-0.1.8.dist-info/LICENSE
xturing-0.1.8.dist-info/METADATA
xturing-0.1.8.dist-info/WHEEL
xturing-0.1.8.dist-info/entry_points.txt
xturing-0.1.8.dist-info/top_level.txt
xturing-0.1.8.dist-info/RECORD
