Metadata-Version: 2.1
Name: xturing
Version: 0.1.8
Summary: Fine-tuning, evaluation and data generation for LLMs
Author-email: Glenn Ko <glenn@stochastic.ai>, Yuji Chai <yuji.chai@stochastic.ai>, Roman Ageev <roman.ageev@stochastic.ai>, Toan Do <toan.do@stochastic.ai>, Marcos R M <marcos.rm@stochastic.ai>, Sarthak Langde <sarthak.langde@stochastic.ai>, Riccardo Romagnoli <riccardo.romagnoli@stochastic.ai>, Subhash G N <subhash.gn@stochastic.ai>
License: Apache License
Project-URL: homepage, https://xturing.stochastic.ai/
Project-URL: documentation, https://github.com/stochasticai/xturing-docs
Project-URL: repository, https://github.com/stochasticai/xturing
Keywords: nlp,llm,finetuning,evaluation,data-generation,training,distributed
Classifier: Development Status :: 3 - Alpha
Classifier: Intended Audience :: Developers
Classifier: Intended Audience :: Science/Research
Classifier: License :: OSI Approved :: Apache Software License
Classifier: Programming Language :: Python :: 3
Classifier: Programming Language :: Python :: 3.7
Classifier: Programming Language :: Python :: 3.8
Classifier: Programming Language :: Python :: 3.9
Classifier: Topic :: Scientific/Engineering :: Artificial Intelligence
Classifier: Topic :: Scientific/Engineering :: Information Analysis
Classifier: Topic :: Software Development :: Libraries :: Python Modules
Classifier: Topic :: Text Processing :: Linguistic
Requires-Python: >=3.7
License-File: LICENSE
Requires-Dist: torch >=1.9.0
Requires-Dist: pytorch-lightning
Requires-Dist: transformers ==4.31.0
Requires-Dist: datasets ==2.14.5
Requires-Dist: evaluate ==0.4.0
Requires-Dist: bitsandbytes ==0.41.1
Requires-Dist: sentencepiece
Requires-Dist: deepspeed ==0.9.5
Requires-Dist: gradio
Requires-Dist: click
Requires-Dist: wget
Requires-Dist: ai21
Requires-Dist: cohere
Requires-Dist: ipywidgets
Requires-Dist: openai >=0.27.0
Requires-Dist: pydantic >=1.10.0
Requires-Dist: rouge-score >=0.1.2
Requires-Dist: accelerate ==0.22.0
Requires-Dist: wandb
Provides-Extra: int4
Requires-Dist: torch >=2.0 ; extra == 'int4'
